playfab/PlayFabAdminAPI.py
playfab/PlayFabAuthenticationAPI.py
playfab/PlayFabClientAPI.py
playfab/PlayFabCloudScriptAPI.py
playfab/PlayFabDataAPI.py
playfab/PlayFabErrors.py
playfab/PlayFabEventsAPI.py
playfab/PlayFabExperimentationAPI.py
playfab/PlayFabGroupsAPI.py
playfab/PlayFabHTTP.py
playfab/PlayFabInsightsAPI.py
playfab/PlayFabLocalizationAPI.py
playfab/PlayFabManualTest.py
playfab/PlayFabMatchmakerAPI.py
playfab/PlayFabMultiplayerAPI.py
playfab/PlayFabProfilesAPI.py
playfab/PlayFabServerAPI.py
playfab/PlayFabSettings.py
playfab/__init__.py
playfab/testCompile.py
playfab-0.0.201014.dist-info/LICENSE
playfab-0.0.201014.dist-info/METADATA
playfab-0.0.201014.dist-info/WHEEL
playfab-0.0.201014.dist-info/top_level.txt
playfab-0.0.201014.dist-info/RECORD
