Metadata-Version: 2.1
Name: playfab
Version: 0.0.201014
Summary: PlayFab Python SDK current API version: 0.0.201014
Home-page: https://github.com/PlayFab/PythonSdk
Author: PlayFab Dev Tools team
Author-email: helloplayfab@microsoft.com
License: UNKNOWN
Platform: UNKNOWN
Classifier: Programming Language :: Python :: 3
Classifier: License :: OSI Approved :: Apache Software License
Classifier: Operating System :: OS Independent
Classifier: Topic :: Games/Entertainment
Requires-Dist: requests
